{"provider_url": "http://twitter.com", "description": "Cooper Union Board chairman Mark Epstein surrounded by students calling for transparency #CULockIn #savecooper pic.twitter.com/pJTLbS7o", "embeds": [], "safe": true, "provider_display": "twitter.com", "related": [], "favicon_url": "https://abs.twimg.com/favicons/favicon.ico", "authors": [{"url": "http://twitter.com/FreeCooperUnion", "name": "FreeCooperUnion"}], "images": [{"caption": null, "url": "https://pbs.twimg.com/media/A9X_MtjCAAA8E0f.jpg:large", "height": 643, "width": 960, "colors": [{"color": [83, 86, 91], "weight": 0.232177734375}, {"color": [27, 31, 41], "weight": 0.223876953125}, {"color": [129, 136, 147], "weight": 0.19970703125}, {"color": [175, 174, 178], "weight": 0.178466796875}, {"color": [238, 241, 240], "weight": 0.165771484375}], "entropy": 6.33674850166, "size": 106377}, {"caption": null, "url": "https://pbs.twimg.com/media/A9X_MtjCAAA8E0f.jpg", "height": 402, "width": 600, "colors": [{"color": [83, 86, 92], "weight": 0.237548828125}, {"color": [27, 30, 38], "weight": 0.2255859375}, {"color": [126, 135, 146], "weight": 0.188720703125}, {"color": [174, 173, 177], "weight": 0.182861328125}, {"color": [238, 241, 240], "weight": 0.165283203125}], "entropy": 6.329014855872783, "size": 45015}, {"caption": null, "url": "https://pbs.twimg.com/profile_images/2552819317/image_normal.jpg", "height": 48, "width": 48, "colors": [{"color": [245, 246, 248], "weight": 0.325439453125}, {"color": [7, 15, 21], "weight": 0.111328125}, {"color": [113, 112, 116], "weight": 0.033935546875}, {"color": [190, 184, 187], "weight": 0.03369140625}, {"color": [147, 146, 150], "weight": 0.031494140625}], "entropy": 3.6525615933, "size": 7190}, {"caption": null, "url": "https://pbs.twimg.com/profile_images/1814662431/amitVerb_reasonably_small_normal.jpg", "height": 48, "width": 48, "colors": [{"color": [234, 245, 242], "weight": 0.233154296875}, {"color": [41, 42, 39], "weight": 0.12353515625}, {"color": [17, 202, 145], "weight": 0.11767578125}, {"color": [82, 82, 72], "weight": 0.031494140625}, {"color": [171, 156, 149], "weight": 0.03125}], "entropy": 5.5650184414, "size": 7190}, {"caption": null, "url": "https://pbs.twimg.com/profile_images/1941396681/image_normal.jpg", "height": 48, "width": 48, "colors": [{"color": [222, 217, 200], "weight": 0.205322265625}, {"color": [163, 148, 135], "weight": 0.15185546875}, {"color": [28, 25, 32], "weight": 0.10791015625}, {"color": [82, 67, 63], "weight": 0.051025390625}, {"color": [118, 99, 90], "weight": 0.04638671875}], "entropy": 6.370146564504805, "size": 7190}], "cache_age": 84883, "lead": null, "language": "English", "original_url": "http://twitter.com/FreeCooperUnion/status/276407545990610944/photo/1", "url": "https://twitter.com/FreeCooperUnion/status/276407545990610944", "media": {"url": "https://pbs.twimg.com/media/A9X_MtjCAAA8E0f.jpg:large", "width": 960, "type": "photo", "height": 643}, "title": "Twitter / FreeCooperUnion: Cooper Union Board chairman ...", "offset": null, "content": null, "entities": [{"count": 2, "name": "Cooper Union Board"}, {"count": 2, "name": "Mark Epstein"}, {"count": 1, "name": "United States"}], "favicon_colors": [{"color": [241, 248, 251], "weight": 0.031494140625}, {"color": [0, 172, 231], "weight": 0.031005859375}], "keywords": [{"score": 20, "name": "culockin"}, {"score": 20, "name": "savecooper"}, {"score": 20, "name": "pjtlbs7o"}, {"score": 16, "name": "location"}, {"score": 15, "name": "epstein"}, {"score": 12, "name": "tweet"}, {"score": 11, "name": "pic"}, {"score": 11, "name": "transparency"}, {"score": 10, "name": "40404"}, {"score": 10, "name": "freecooperunion"}], "published": null, "provider_name": "Twitter", "type": "html"}