{"provider_url": "http://twitter.com", "description": "It ain't over 'til its over! The banner flies again. #day3 pic.twitter.com/KCrZaEMlEA", "embeds": [], "safe": true, "provider_display": "twitter.com", "related": [], "favicon_url": "https://abs.twimg.com/favicons/favicon.ico", "authors": [{"url": "http://twitter.com/FreeCooperUnion", "name": "FreeCooperUnion"}], "images": [{"caption": null, "url": "https://pbs.twimg.com/media/BIto_xzCYAA2a3r.jpg:large", "height": 1024, "width": 765, "colors": [{"color": [194, 175, 165], "weight": 0.24658203125}, {"color": [32, 30, 30], "weight": 0.244384765625}, {"color": [88, 148, 231], "weight": 0.112060546875}, {"color": [157, 143, 135], "weight": 0.095703125}, {"color": [123, 115, 110], "weight": 0.085205078125}], "entropy": 6.83837453458, "size": 187511}, {"caption": null, "url": "https://pbs.twimg.com/media/BIto_xzCYAA2a3r.jpg", "height": 803, "width": 599, "colors": [{"color": [31, 29, 29], "weight": 0.250244140625}, {"color": [193, 173, 161], "weight": 0.244140625}, {"color": [72, 73, 74], "weight": 0.13427734375}, {"color": [90, 147, 228], "weight": 0.109375}, {"color": [156, 142, 134], "weight": 0.1064453125}], "entropy": 6.8980874154440315, "size": 129819}, {"caption": null, "url": "https://pbs.twimg.com/profile_images/3452266700/3864ed9f791769e33f08a8e2b6e485f5_normal.jpeg", "height": 48, "width": 48, "colors": [{"color": [245, 251, 245], "weight": 0.33251953125}, {"color": [234, 193, 46], "weight": 0.086181640625}, {"color": [30, 12, 4], "weight": 0.049560546875}, {"color": [85, 64, 21], "weight": 0.036865234375}, {"color": [131, 106, 34], "weight": 0.026611328125}], "entropy": 4.50886523827, "size": 7190}, {"caption": null, "url": "https://pbs.twimg.com/profile_images/378800000470829383/948759330de817b1e16adf37384bcb88_normal.jpeg", "height": 48, "width": 48, "colors": [{"color": [238, 200, 126], "weight": 0.205078125}, {"color": [14, 24, 32], "weight": 0.169189453125}, {"color": [0, 87, 160], "weight": 0.056884765625}, {"color": [26, 57, 81], "weight": 0.0380859375}, {"color": [188, 153, 89], "weight": 0.035888671875}], "entropy": 6.00971401657, "size": 7190}, {"caption": null, "url": "https://pbs.twimg.com/profile_images/1730785632/284424_2165421488668_1040571605_4453804_7550906_n_normal.jpg", "height": 48, "width": 48, "colors": [{"color": [207, 216, 222], "weight": 0.41259765625}, {"color": [63, 46, 26], "weight": 0.091796875}, {"color": [107, 94, 68], "weight": 0.033447265625}, {"color": [115, 127, 124], "weight": 0.024658203125}], "entropy": 5.13910408034, "size": 7190}], "cache_age": 86400, "lead": null, "language": "English", "original_url": "http://twitter.com/FreeCooperUnion/status/327470842814554112/photo/1", "url": "https://twitter.com/FreeCooperUnion/status/327470842814554112", "media": {"url": "https://pbs.twimg.com/media/BIto_xzCYAA2a3r.jpg:large", "width": 765, "type": "photo", "height": 1024}, "title": "Twitter / FreeCooperUnion: It ain't over 'til its over! ...", "offset": null, "content": null, "entities": [{"count": 1, "name": "United States"}], "favicon_colors": [{"color": [241, 248, 251], "weight": 0.03662109375}, {"color": [0, 172, 231], "weight": 0.02587890625}], "keywords": [{"score": 30, "name": "day3"}, {"score": 20, "name": "kcrzaemlea"}, {"score": 20, "name": "freecooperunion"}, {"score": 19, "name": "ain"}, {"score": 18, "name": "banner"}, {"score": 17, "name": "pic"}, {"score": 16, "name": "location"}, {"score": 13, "name": "twitter"}, {"score": 12, "name": "flies"}, {"score": 10, "name": "40404"}], "published": null, "provider_name": "Twitter", "type": "html"}