{"provider_url": "http://www.facebook.com", "description": "JOINT STATEMENT FROM THE LEADERSHIP OF CUFCT, CUOP, AND U@CU The faculty and staff unions at The Cooper Union deeply regret the Board of Trustees' vote...", "embeds": [], "safe": true, "provider_display": "www.facebook.com", "related": [], "favicon_url": "https://fbstatic-a.akamaihd.net/rsrc.php/yV/r/hzMapiNYYpW.ico", "authors": [{"url": "https://www.facebook.com/CooperUnionOrganizationOfPartTimeFaculty", "name": "CooperUnionOrganizationOfPartTimeFaculty"}], "images": [{"url": "https://fbcdn-profile-a.akamaihd.net/hprofile-ak-prn2/261185_464391836945393_1202177789_q.jpg", "width": 50, "size": 2509, "caption": null, "height": 50}], "cache_age": 86400, "lead": null, "language": null, "original_url": "https://www.facebook.com/CooperUnionOrganizationOfPartTimeFaculty/posts/529646647086578", "url": "https://www.facebook.com/CooperUnionOrganizationOfPartTimeFaculty/posts/529646647086578", "media": {"width": null, "html": "<div id=\"fb-root\"></div><script type=\"text/javascript\" src=\"https://connect.facebook.net/en_US/all.js#xfbml=1\"></script><div class=\"fb-post\" data-href=\"https://www.facebook.com/CooperUnionOrganizationOfPartTimeFaculty/posts/529646647086578\"><div class=\"fb-xfbml-parse-ignore\"><a href=\"https://www.facebook.com/CooperUnionOrganizationOfPartTimeFaculty/posts/529646647086578\">Post</a> by <a href=\"https://www.facebook.com/CooperUnionOrganizationOfPartTimeFaculty\">CooperUnionOrganizationOfPartTimeFaculty</a>.</div></div>", "type": "rich", "height": null}, "title": "JOINT STATEMENT FROM THE LEADERSHIP OF... - Cooper Union Organization of Part-Time Faculty | Facebook", "offset": null, "content": null, "entities": [], "favicon_colors": [{"color": [54, 97, 163], "weight": 0.040283203125}, {"color": [0, 0, 0], "weight": 0.012939453125}, {"color": [243, 245, 249], "weight": 0.00927734375}], "keywords": [], "published": null, "provider_name": "Facebook", "type": "html"}