{"provider_url": "http://twitter.com", "description": "\"TAKE BACK COOPER UNION\" Stop Shopping Choir laying outside the Foundation Building, singing and chanting to us! pic.twitter.com/ImBq35hGKP", "embeds": [], "safe": true, "provider_display": "twitter.com", "related": [], "favicon_url": "https://abs.twimg.com/favicons/favicon.ico", "authors": [{"url": "http://twitter.com/FreeCooperUnion", "name": "FreeCooperUnion"}], "images": [{"caption": null, "url": "https://pbs.twimg.com/media/BLOfQyPCQAEedsa.jpg:large", "height": 765, "width": 1024, "colors": [{"color": [34, 58, 31], "weight": 0.28076171875}, {"color": [204, 213, 206], "weight": 0.25439453125}, {"color": [73, 112, 44], "weight": 0.14990234375}, {"color": [145, 155, 149], "weight": 0.13427734375}, {"color": [100, 106, 97], "weight": 0.121337890625}], "entropy": 7.00367579797, "size": 118176}, {"caption": null, "url": "https://pbs.twimg.com/media/BLOfQyPCQAEedsa.jpg", "height": 448, "width": 599, "colors": [{"color": [205, 212, 205], "weight": 0.25048828125}, {"color": [44, 68, 39], "weight": 0.16845703125}, {"color": [73, 112, 44], "weight": 0.156494140625}, {"color": [144, 153, 149], "weight": 0.1337890625}, {"color": [100, 105, 94], "weight": 0.1181640625}], "entropy": 7.040737073168491, "size": 52829}, {"caption": null, "url": "https://pbs.twimg.com/profile_images/378800000763160764/878632134576e75626199ce67b0c39b4_normal.jpeg", "height": 48, "width": 48, "colors": [{"color": [236, 237, 239], "weight": 0.3515625}, {"color": [49, 52, 58], "weight": 0.12353515625}, {"color": [110, 114, 120], "weight": 0.08740234375}], "entropy": 3.35137282142, "size": 1761}, {"caption": null, "url": "https://pbs.twimg.com/profile_images/592205297/foto_mam-1_normal.jpg", "height": 48, "width": 48, "colors": [{"color": [73, 67, 65], "weight": 0.211181640625}, {"color": [29, 27, 28], "weight": 0.153564453125}, {"color": [217, 217, 229], "weight": 0.0966796875}, {"color": [168, 166, 178], "weight": 0.0537109375}, {"color": [141, 131, 120], "weight": 0.04736328125}], "entropy": 5.81917110067, "size": 7190}, {"caption": null, "url": "https://pbs.twimg.com/profile_images/3438227748/fe748fcba19f6f439935188bddff43e1_normal.jpeg", "height": 48, "width": 48, "colors": [{"color": [25, 22, 22], "weight": 0.27001953125}, {"color": [199, 207, 215], "weight": 0.148193359375}, {"color": [129, 136, 144], "weight": 0.144287109375}], "entropy": 5.00536196044, "size": 7190}], "cache_age": 86400, "lead": null, "language": "English", "original_url": "http://twitter.com/FreeCooperUnion/status/338789507686088704/photo/1", "url": "https://twitter.com/FreeCooperUnion/status/338789507686088704", "media": {"url": "https://pbs.twimg.com/media/BLOfQyPCQAEedsa.jpg:large", "width": 1024, "type": "photo", "height": 765}, "title": "Twitter / FreeCooperUnion: \"TAKE BACK COOPER UNION\" Stop ...", "offset": null, "content": null, "entities": [{"count": 1, "name": "United States"}], "favicon_colors": [{"color": [241, 248, 251], "weight": 0.032470703125}, {"color": [0, 172, 233], "weight": 0.030029296875}], "keywords": [{"score": 20, "name": "imbq35hgkp"}, {"score": 16, "name": "location"}, {"score": 14, "name": "choir"}, {"score": 12, "name": "tweet"}, {"score": 11, "name": "pic"}, {"score": 11, "name": "chanting"}, {"score": 10, "name": "40404"}, {"score": 10, "name": "singing"}, {"score": 10, "name": "freecooperunion"}, {"score": 9, "name": "twitter"}], "published": null, "provider_name": "Twitter", "type": "html"}