{"provider_url": "http://twitter.com", "description": "Mark Epstein's statement to be followed by questions pic.twitter.com/HEyGNeDqZU", "embeds": [], "safe": true, "provider_display": "twitter.com", "related": [], "favicon_url": "https://abs.twimg.com/favicons/favicon.ico", "authors": [{"url": "http://twitter.com/FreeCooperUnion", "name": "FreeCooperUnion"}], "images": [{"caption": null, "url": "https://pbs.twimg.com/media/BIjGTySCMAIgV7y.jpg:large", "height": 765, "width": 1024, "colors": [{"color": [136, 116, 98], "weight": 0.380615234375}, {"color": [96, 61, 40], "weight": 0.263916015625}, {"color": [40, 23, 17], "weight": 0.21435546875}, {"color": [186, 178, 163], "weight": 0.080078125}, {"color": [230, 233, 222], "weight": 0.06103515625}], "entropy": 6.45229647624, "size": 82151}, {"caption": null, "url": "https://pbs.twimg.com/media/BIjGTySCMAIgV7y.jpg", "height": 448, "width": 599, "colors": [{"color": [132, 112, 94], "weight": 0.39306640625}, {"color": [93, 58, 38], "weight": 0.24853515625}, {"color": [40, 23, 17], "weight": 0.2119140625}, {"color": [180, 170, 155], "weight": 0.087890625}, {"color": [229, 229, 217], "weight": 0.05859375}], "entropy": 6.436144910767417, "size": 34511}, {"caption": null, "url": "https://pbs.twimg.com/profile_images/378800000831796892/3279fb8343bd096dcb6527135e38c0d2_normal.jpeg", "height": 48, "width": 48, "colors": [{"color": [0, 2, 6], "weight": 0.25390625}, {"color": [238, 236, 31], "weight": 0.180908203125}, {"color": [168, 169, 38], "weight": 0.051513671875}, {"color": [128, 125, 19], "weight": 0.038330078125}, {"color": [75, 73, 4], "weight": 0.037841796875}], "entropy": 4.20562174251, "size": 2177}, {"caption": null, "url": "https://pbs.twimg.com/profile_images/3646250943/ae5f55f4147e601f83ad3235b0d65418_normal.png", "height": 48, "width": 48, "colors": [{"color": [225, 28, 19], "weight": 0.441650390625}, {"color": [242, 164, 148], "weight": 0.120849609375}], "entropy": 2.38717929669, "size": 7190}], "cache_age": 86400, "lead": null, "language": "English", "original_url": "http://twitter.com/FreeCooperUnion/status/326729016197394432/photo/1", "url": "https://twitter.com/FreeCooperUnion/status/326729016197394432", "media": {"url": "https://pbs.twimg.com/media/BIjGTySCMAIgV7y.jpg:large", "width": 1024, "type": "photo", "height": 765}, "title": "Twitter / FreeCooperUnion: Mark Epstein's statement to ...", "offset": null, "content": null, "entities": [{"count": 2, "name": "Mark Epstein"}, {"count": 1, "name": "United States"}], "favicon_colors": [{"color": [241, 248, 251], "weight": 0.03662109375}, {"color": [0, 172, 231], "weight": 0.02587890625}], "keywords": [{"score": 20, "name": "heygnedqzu"}, {"score": 16, "name": "location"}, {"score": 15, "name": "epstein"}, {"score": 12, "name": "tweet"}, {"score": 11, "name": "pic"}, {"score": 10, "name": "40404"}, {"score": 10, "name": "freecooperunion"}, {"score": 9, "name": "marked"}, {"score": 9, "name": "twitter"}, {"score": 7, "name": "learn"}], "published": null, "provider_name": "Twitter", "type": "html"}