{"provider_url": "http://twitter.com", "description": "\"We are students NOT customers\" @FreeCooperUnion! #maydaynyc pic.twitter.com/kpnRXKtfEM", "embeds": [], "safe": true, "provider_display": "twitter.com", "related": [], "favicon_url": "https://abs.twimg.com/favicons/favicon.ico", "authors": [{"url": "http://twitter.com/illuminator99", "name": "illuminator99"}], "images": [{"caption": null, "url": "https://pbs.twimg.com/media/BJOzCwsCUAEmuo8.jpg:large", "height": 682, "width": 1024, "colors": [{"color": [10, 15, 12], "weight": 0.53076171875}, {"color": [45, 48, 49], "weight": 0.141357421875}, {"color": [113, 118, 100], "weight": 0.10888671875}, {"color": [86, 67, 44], "weight": 0.092529296875}, {"color": [235, 242, 234], "weight": 0.05126953125}], "entropy": 5.66760000835, "size": 82880}, {"caption": null, "url": "https://pbs.twimg.com/media/BJOzCwsCUAEmuo8.jpg", "height": 400, "width": 600, "colors": [{"color": [9, 14, 10], "weight": 0.5048828125}, {"color": [45, 43, 40], "weight": 0.119873046875}, {"color": [91, 83, 66], "weight": 0.09912109375}, {"color": [79, 54, 31], "weight": 0.083251953125}, {"color": [117, 124, 108], "weight": 0.0546875}], "entropy": 5.557656189211596, "size": 33461}, {"caption": null, "url": "https://pbs.twimg.com/profile_images/1842309610/99_percent_circleTEXT6_normal.jpg", "height": 48, "width": 48, "colors": [{"color": [231, 231, 231], "weight": 0.3818359375}, {"color": [23, 23, 23], "weight": 0.1806640625}], "entropy": 2.85308274299, "size": 7190}, {"caption": null, "url": "https://pbs.twimg.com/profile_images/1853919756/OccupyUNLV_normal.jpg", "height": 48, "width": 48, "colors": [{"color": [207, 38, 57], "weight": 0.18896484375}, {"color": [240, 240, 240], "weight": 0.098876953125}, {"color": [0, 4, 5], "weight": 0.072509765625}, {"color": [179, 150, 156], "weight": 0.04736328125}, {"color": [159, 106, 116], "weight": 0.034912109375}], "entropy": 5.33273055059, "size": 31952}, {"caption": null, "url": "https://pbs.twimg.com/profile_images/3505112962/b7c5784a1e79b9db8b15faff3dfc1c4a_normal.jpeg", "height": 48, "width": 48, "colors": [{"color": [102, 78, 69], "weight": 0.193359375}, {"color": [122, 128, 134], "weight": 0.190185546875}, {"color": [52, 37, 31], "weight": 0.0908203125}, {"color": [155, 190, 213], "weight": 0.088134765625}], "entropy": 6.3838264017, "size": 7190}], "cache_age": 86400, "lead": null, "language": "English", "original_url": "http://twitter.com/illuminator99/status/329804057734696960/photo/1", "url": "https://twitter.com/illuminator99/status/329804057734696960", "media": {"url": "https://pbs.twimg.com/media/BJOzCwsCUAEmuo8.jpg:large", "width": 1024, "type": "photo", "height": 682}, "title": "Twitter / illuminator99: \"We are students NOT customers\" ...", "offset": null, "content": null, "entities": [{"count": 1, "name": "United States"}], "favicon_colors": [{"color": [0, 174, 233], "weight": 0.03173828125}, {"color": [239, 247, 252], "weight": 0.03076171875}], "keywords": [{"score": 20, "name": "kpnrxktfem"}, {"score": 20, "name": "maydaynyc"}, {"score": 20, "name": "freecooperunion"}, {"score": 16, "name": "location"}, {"score": 12, "name": "tweet"}, {"score": 11, "name": "pic"}, {"score": 10, "name": "illuminator99"}, {"score": 10, "name": "40404"}, {"score": 9, "name": "twitter"}, {"score": 8, "name": "customers"}], "published": null, "provider_name": "Twitter", "type": "html"}