{"provider_url": "http://twitter.com", "description": "Student Occupiers via Skype @FreeCooperUnion pic.twitter.com/psqCIhCl", "embeds": [], "safe": true, "provider_display": "twitter.com", "related": [], "favicon_url": "https://abs.twimg.com/favicons/favicon.ico", "authors": [{"url": "http://twitter.com/literaryanimal", "name": "literaryanimal"}], "images": [{"caption": null, "url": "https://pbs.twimg.com/media/A9PAWRbCMAA4zz1.jpg:large", "height": 768, "width": 1024, "colors": [{"color": [119, 101, 74], "weight": 0.3955078125}, {"color": [22, 16, 11], "weight": 0.25830078125}, {"color": [68, 50, 30], "weight": 0.258056640625}, {"color": [178, 170, 147], "weight": 0.052490234375}, {"color": [234, 242, 228], "weight": 0.03564453125}], "entropy": 6.19359237391, "size": 86868}, {"caption": null, "url": "https://pbs.twimg.com/media/A9PAWRbCMAA4zz1.jpg", "height": 450, "width": 600, "colors": [{"color": [125, 106, 77], "weight": 0.381103515625}, {"color": [72, 54, 31], "weight": 0.288818359375}, {"color": [25, 18, 12], "weight": 0.253662109375}, {"color": [182, 175, 148], "weight": 0.04345703125}, {"color": [229, 242, 226], "weight": 0.032958984375}], "entropy": 6.2360004559503395, "size": 40245}, {"caption": null, "url": "https://pbs.twimg.com/profile_images/2853516701/525cf2659d2950344894952fecb065fc_normal.jpeg", "height": 48, "width": 48, "colors": [{"color": [240, 246, 247], "weight": 0.26611328125}, {"color": [19, 21, 21], "weight": 0.125}, {"color": [181, 161, 147], "weight": 0.084716796875}, {"color": [138, 105, 93], "weight": 0.05517578125}, {"color": [93, 73, 65], "weight": 0.031494140625}], "entropy": 5.10745879218, "size": 1047}, {"caption": null, "url": "https://pbs.twimg.com/profile_images/378800000470829383/948759330de817b1e16adf37384bcb88_normal.jpeg", "height": 48, "width": 48, "colors": [{"color": [238, 200, 126], "weight": 0.205078125}, {"color": [14, 24, 32], "weight": 0.169189453125}, {"color": [0, 87, 160], "weight": 0.056884765625}, {"color": [26, 57, 81], "weight": 0.0380859375}, {"color": [188, 153, 89], "weight": 0.035888671875}], "entropy": 6.00971401657, "size": 7190}, {"caption": null, "url": "https://pbs.twimg.com/profile_images/1766569774/sj2b_normal.jpg", "height": 48, "width": 48, "colors": [{"color": [217, 212, 216], "weight": 0.363037109375}, {"color": [68, 53, 56], "weight": 0.114501953125}, {"color": [119, 108, 111], "weight": 0.0849609375}], "entropy": 4.68417864662, "size": 7190}], "cache_age": 86400, "lead": null, "language": "Italian", "original_url": "http://twitter.com/literaryanimal/status/275775491061985280/photo/1", "url": "https://twitter.com/literaryanimal/status/275775491061985280", "media": {"url": "https://pbs.twimg.com/media/A9PAWRbCMAA4zz1.jpg:large", "width": 1024, "type": "photo", "height": 768}, "title": "Twitter / literaryanimal: Student Occupiers via Skype ...", "offset": null, "content": null, "entities": [], "favicon_colors": [{"color": [0, 174, 233], "weight": 0.03173828125}, {"color": [239, 247, 252], "weight": 0.03076171875}], "keywords": [], "published": null, "provider_name": "Twitter", "type": "html"}