{"provider_url": "http://twitter.com", "description": "NYPD paddy wagon just pulled up outside of Cooper Union. @FreeCooperUnion pic.twitter.com/gYBB4MSOkK", "embeds": [], "safe": true, "provider_display": "twitter.com", "related": [], "favicon_url": "https://abs.twimg.com/favicons/favicon.ico", "authors": [{"url": "http://twitter.com/sydbrownstone", "name": "sydbrownstone"}], "images": [{"caption": null, "url": "https://pbs.twimg.com/media/BJxNl1GCQAAwuTv.jpg:large", "height": 765, "width": 1024, "colors": [{"color": [85, 83, 78], "weight": 0.453125}, {"color": [25, 27, 24], "weight": 0.30322265625}, {"color": [136, 143, 141], "weight": 0.142822265625}, {"color": [209, 220, 224], "weight": 0.100830078125}], "entropy": 6.16249406871, "size": 117965}, {"caption": null, "url": "https://pbs.twimg.com/media/BJxNl1GCQAAwuTv.jpg", "height": 448, "width": 599, "colors": [{"color": [70, 68, 64], "weight": 0.31494140625}, {"color": [19, 22, 20], "weight": 0.275146484375}, {"color": [105, 103, 98], "weight": 0.190185546875}, {"color": [138, 140, 143], "weight": 0.10693359375}, {"color": [223, 234, 238], "weight": 0.06591796875}], "entropy": 6.265457416042618, "size": 49381}, {"caption": null, "url": "https://pbs.twimg.com/profile_images/3699547625/399379b5914d501c70a6d90356ba2f70_normal.jpeg", "height": 48, "width": 48, "colors": [{"color": [131, 117, 88], "weight": 0.094970703125}, {"color": [98, 90, 80], "weight": 0.09228515625}, {"color": [67, 58, 48], "weight": 0.08203125}, {"color": [235, 244, 237], "weight": 0.066162109375}, {"color": [35, 31, 26], "weight": 0.0595703125}], "entropy": 6.6928185834, "size": 7190}], "cache_age": 86400, "lead": null, "language": "English", "original_url": "http://twitter.com/sydbrownstone/status/332225784813076482/photo/1", "url": "https://twitter.com/sydbrownstone/status/332225784813076482", "media": {"url": "https://pbs.twimg.com/media/BJxNl1GCQAAwuTv.jpg:large", "width": 1024, "type": "photo", "height": 765}, "title": "Twitter / sydbrownstone: NYPD paddy wagon just pulled ...", "offset": null, "content": null, "entities": [{"count": 2, "name": "NYPD"}, {"count": 2, "name": "Cooper Union"}, {"count": 1, "name": "United States"}], "favicon_colors": [{"color": [0, 174, 233], "weight": 0.03173828125}, {"color": [239, 247, 252], "weight": 0.03076171875}], "keywords": [{"score": 20, "name": "gybb4msokk"}, {"score": 20, "name": "freecooperunion"}, {"score": 17, "name": "paddy"}, {"score": 16, "name": "location"}, {"score": 15, "name": "wagon"}, {"score": 15, "name": "nypd"}, {"score": 12, "name": "tweet"}, {"score": 11, "name": "pic"}, {"score": 10, "name": "40404"}, {"score": 10, "name": "sydbrownstone"}], "published": null, "provider_name": "Twitter", "type": "html"}