{"provider_url": "http://twitter.com", "description": "CUNY Prof speaks: \"I want you to know many, MANY faculty are behind you!\" pic.twitter.com/s9hW096WRd", "embeds": [], "safe": true, "provider_display": "twitter.com", "related": [], "favicon_url": "https://abs.twimg.com/favicons/favicon.ico", "authors": [{"url": "http://twitter.com/FreeCooperUnion", "name": "FreeCooperUnion"}], "images": [{"caption": null, "url": "https://pbs.twimg.com/media/BXHg-zrIgAArGQj.jpg:large", "height": 296, "width": 1024, "colors": [{"color": [72, 63, 69], "weight": 0.414794921875}, {"color": [34, 29, 37], "weight": 0.3193359375}, {"color": [125, 110, 115], "weight": 0.200439453125}, {"color": [234, 238, 239], "weight": 0.033203125}, {"color": [180, 175, 176], "weight": 0.0322265625}], "entropy": 6.09421035854, "size": 51066}, {"caption": null, "url": "https://pbs.twimg.com/media/BXHg-zrIgAArGQj.jpg", "height": 173, "width": 598, "colors": [{"color": [84, 70, 77], "weight": 0.398193359375}, {"color": [40, 34, 41], "weight": 0.324462890625}, {"color": [126, 111, 116], "weight": 0.105712890625}, {"color": [190, 180, 179], "weight": 0.065673828125}, {"color": [152, 142, 145], "weight": 0.0576171875}], "entropy": 6.519738001912939, "size": 22536}, {"caption": null, "url": "https://pbs.twimg.com/profile_images/378800000847957720/c4226fa4db8367cb1902dc8f07620054_normal.jpeg", "height": 48, "width": 48, "colors": [{"color": [125, 123, 123], "weight": 0.28369140625}, {"color": [177, 185, 189], "weight": 0.10595703125}, {"color": [24, 20, 19], "weight": 0.07763671875}, {"color": [94, 80, 75], "weight": 0.060546875}, {"color": [70, 55, 51], "weight": 0.03466796875}], "entropy": 5.92448738902, "size": 1868}, {"caption": null, "url": "https://pbs.twimg.com/profile_images/1901603588/tjc_small_normal.jpg", "height": 48, "width": 48, "colors": [{"color": [123, 100, 89], "weight": 0.2373046875}, {"color": [77, 58, 49], "weight": 0.169921875}, {"color": [229, 221, 211], "weight": 0.09521484375}, {"color": [179, 166, 156], "weight": 0.06005859375}], "entropy": 6.52101265109, "size": 7190}, {"caption": null, "url": "https://pbs.twimg.com/profile_images/1693628082/IMG_9502_normal.jpg", "height": 48, "width": 48, "colors": [{"color": [87, 87, 96], "weight": 0.171630859375}, {"color": [22, 15, 17], "weight": 0.137451171875}, {"color": [72, 47, 49], "weight": 0.123046875}, {"color": [165, 77, 87], "weight": 0.05224609375}, {"color": [129, 113, 107], "weight": 0.03564453125}], "entropy": 6.15776384816, "size": 7190}], "cache_age": 86400, "lead": null, "language": "English", "original_url": "http://twitter.com/FreeCooperUnion/status/392342012328169472/photo/1", "url": "https://twitter.com/FreeCooperUnion/status/392342012328169472", "media": {"url": "https://pbs.twimg.com/media/BXHg-zrIgAArGQj.jpg:large", "width": 1024, "type": "photo", "height": 296}, "title": "Twitter / FreeCooperUnion: CUNY Prof speaks: \"I want you ...", "offset": null, "content": null, "entities": [{"count": 2, "name": "CUNY"}, {"count": 1, "name": "United States"}], "favicon_colors": [{"color": [246, 250, 251], "weight": 0.03173828125}, {"color": [0, 171, 230], "weight": 0.03076171875}], "keywords": [{"score": 20, "name": "s9hw096wrd"}, {"score": 17, "name": "cuny"}, {"score": 16, "name": "location"}, {"score": 13, "name": "faculty"}, {"score": 12, "name": "tweet"}, {"score": 12, "name": "prof"}, {"score": 11, "name": "pic"}, {"score": 10, "name": "40404"}, {"score": 10, "name": "freecooperunion"}, {"score": 9, "name": "twitter"}], "published": null, "provider_name": "Twitter", "type": "html"}