{"provider_url": "http://twitter.com", "description": "From @hayskali, the first photo from inside the @FreeCooperUnion occupation. Follow our live blog: http://bit.ly/11Hh5i0 pic.twitter.com/8iA1QmSf", "embeds": [], "safe": true, "provider_display": "twitter.com", "related": [], "favicon_url": "https://abs.twimg.com/favicons/favicon.ico", "authors": [{"url": "http://twitter.com/NSFreePress", "name": "NSFreePress"}], "images": [{"caption": null, "url": "https://pbs.twimg.com/media/A9NQxj4CQAAK0ig.jpg:large", "height": 804, "width": 600, "colors": [{"color": [23, 22, 24], "weight": 0.569091796875}, {"color": [67, 64, 66], "weight": 0.27099609375}, {"color": [237, 244, 244], "weight": 0.10546875}, {"color": [133, 135, 138], "weight": 0.028564453125}, {"color": [173, 175, 178], "weight": 0.02587890625}], "entropy": 4.73945869854, "size": 44299}, {"caption": null, "url": "https://pbs.twimg.com/media/A9NQxj4CQAAK0ig.jpg", "height": 804, "width": 600, "colors": [{"color": [21, 19, 21], "weight": 0.58203125}, {"color": [61, 58, 60], "weight": 0.309814453125}, {"color": [238, 247, 247], "weight": 0.07958984375}, {"color": [142, 144, 147], "weight": 0.028564453125}], "entropy": 4.595794891797454, "size": 44299}, {"caption": null, "url": "https://pbs.twimg.com/profile_images/2547385769/d5qj8j7ncpb7s08bkfrr_normal.jpeg", "height": 48, "width": 48, "colors": [{"color": [244, 248, 249], "weight": 0.248779296875}, {"color": [0, 4, 5], "weight": 0.171875}, {"color": [81, 84, 85], "weight": 0.056640625}, {"color": [148, 151, 152], "weight": 0.045654296875}, {"color": [191, 195, 196], "weight": 0.03955078125}], "entropy": 2.9612396859518784, "size": 7190}, {"caption": null, "url": "https://pbs.twimg.com/profile_images/2591004242/tbfcy7cdw08xa7rr7iqi_normal.jpeg", "height": 48, "width": 48, "colors": [{"color": [240, 229, 213], "weight": 0.123291015625}, {"color": [109, 81, 70], "weight": 0.10791015625}, {"color": [135, 115, 111], "weight": 0.103271484375}, {"color": [68, 49, 40], "weight": 0.089599609375}, {"color": [35, 20, 14], "weight": 0.06982421875}], "entropy": 6.400868179058926, "size": 7190}, {"caption": null, "url": "https://pbs.twimg.com/profile_images/378800000212528277/037d4c9d0106f0a7334e9b090fdc98a0_normal.jpeg", "height": 48, "width": 48, "colors": [{"color": [107, 127, 115], "weight": 0.25341796875}, {"color": [159, 164, 151], "weight": 0.1044921875}, {"color": [84, 86, 86], "weight": 0.09326171875}, {"color": [219, 215, 200], "weight": 0.081298828125}, {"color": [67, 47, 46], "weight": 0.030029296875}], "entropy": 6.4722250081648145, "size": 1123}], "cache_age": 83145, "lead": null, "language": "English", "original_url": "http://twitter.com/NSFreePress/status/275652814565425153/photo/1", "url": "https://twitter.com/NSFreePress/status/275652814565425153", "media": {"url": "https://pbs.twimg.com/media/A9NQxj4CQAAK0ig.jpg:large", "width": 600, "type": "photo", "height": 804}, "title": "Twitter / NSFreePress: From @hayskali, the first photo ...", "offset": null, "content": null, "entities": [{"count": 1, "name": "United States"}], "favicon_colors": [{"color": [244, 249, 252], "weight": 0.035888671875}, {"color": [0, 172, 231], "weight": 0.026611328125}], "keywords": [{"score": 20, "name": "hayskali"}, {"score": 20, "name": "11hh5i0"}, {"score": 20, "name": "8ia1qmsf"}, {"score": 20, "name": "freecooperunion"}, {"score": 16, "name": "location"}, {"score": 12, "name": "tweet"}, {"score": 11, "name": "pic"}, {"score": 11, "name": "occupation"}, {"score": 10, "name": "40404"}, {"score": 10, "name": "nsfreepress"}], "published": null, "provider_name": "Twitter", "type": "html"}