{"provider_url": "http://twitter.com", "description": "It's still the eleventh hour @cooperunion. Keep it free, keep it wild! pic.twitter.com/dzq5JmWNCL", "embeds": [], "safe": true, "provider_display": "twitter.com", "related": [], "favicon_url": "https://abs.twimg.com/favicons/favicon.ico", "authors": [{"url": "http://twitter.com/FreeCooperUnion", "name": "FreeCooperUnion"}], "images": [{"caption": null, "url": "https://pbs.twimg.com/media/BIs9T-QCYAE2lhX.jpg:large", "height": 612, "width": 960, "colors": [{"color": [93, 87, 78], "weight": 0.892822265625}, {"color": [155, 142, 132], "weight": 0.076904296875}, {"color": [233, 205, 174], "weight": 0.0302734375}], "entropy": 4.73078827664, "size": 68834}, {"caption": null, "url": "https://pbs.twimg.com/media/BIs9T-QCYAE2lhX.jpg", "height": 382, "width": 599, "colors": [{"color": [92, 86, 77], "weight": 0.912353515625}, {"color": [154, 144, 133], "weight": 0.060546875}, {"color": [233, 208, 176], "weight": 0.027099609375}], "entropy": 4.594128903219569, "size": 26812}, {"caption": null, "url": "https://pbs.twimg.com/profile_images/378800000831796892/3279fb8343bd096dcb6527135e38c0d2_normal.jpeg", "height": 48, "width": 48, "colors": [{"color": [0, 2, 6], "weight": 0.25390625}, {"color": [238, 236, 31], "weight": 0.180908203125}, {"color": [168, 169, 38], "weight": 0.051513671875}, {"color": [128, 125, 19], "weight": 0.038330078125}, {"color": [75, 73, 4], "weight": 0.037841796875}], "entropy": 4.20562174251, "size": 2177}], "cache_age": 86400, "lead": null, "language": "English", "original_url": "http://twitter.com/FreeCooperUnion/status/327422811247370241/photo/1", "url": "https://twitter.com/FreeCooperUnion/status/327422811247370241", "media": {"url": "https://pbs.twimg.com/media/BIs9T-QCYAE2lhX.jpg:large", "width": 960, "type": "photo", "height": 612}, "title": "Twitter / FreeCooperUnion: It's still the eleventh hour ...", "offset": null, "content": null, "entities": [{"count": 1, "name": "United States"}], "favicon_colors": [{"color": [241, 248, 251], "weight": 0.03662109375}, {"color": [0, 172, 231], "weight": 0.02587890625}], "keywords": [{"score": 20, "name": "cooperunion"}, {"score": 20, "name": "dzq5jmwncl"}, {"score": 16, "name": "eleventh"}, {"score": 16, "name": "location"}, {"score": 12, "name": "tweet"}, {"score": 11, "name": "pic"}, {"score": 11, "name": "keep"}, {"score": 10, "name": "40404"}, {"score": 10, "name": "freecooperunion"}, {"score": 9, "name": "twitter"}], "published": null, "provider_name": "Twitter", "type": "html"}