{"provider_url": "http://twitter.com", "description": "Drawing class in Peter Cooper Park with @BHQFU, happening now! Sax playing too. pic.twitter.com/y4poSMgk5P", "embeds": [], "safe": true, "provider_display": "twitter.com", "related": [], "favicon_url": "https://abs.twimg.com/favicons/favicon.ico", "authors": [{"url": "http://twitter.com/FreeCooperUnion", "name": "FreeCooperUnion"}], "images": [{"caption": null, "url": "https://pbs.twimg.com/media/BKF1A-kCAAAq0Jq.jpg:large", "height": 765, "width": 1024, "colors": [{"color": [143, 176, 94], "weight": 0.173828125}, {"color": [48, 74, 37], "weight": 0.156005859375}, {"color": [91, 124, 58], "weight": 0.150146484375}, {"color": [223, 243, 172], "weight": 0.129150390625}, {"color": [72, 81, 87], "weight": 0.11572265625}], "entropy": 7.07889471526, "size": 190755}, {"caption": null, "url": "https://pbs.twimg.com/media/BKF1A-kCAAAq0Jq.jpg", "height": 448, "width": 599, "colors": [{"color": [213, 238, 144], "weight": 0.1630859375}, {"color": [96, 129, 63], "weight": 0.14453125}, {"color": [229, 238, 232], "weight": 0.113037109375}, {"color": [148, 182, 93], "weight": 0.11083984375}, {"color": [41, 59, 39], "weight": 0.10791015625}], "entropy": 7.22965127326028, "size": 77661}, {"caption": null, "url": "https://pbs.twimg.com/profile_images/1883949175/cwc_normal.jpg", "height": 48, "width": 48, "colors": [{"color": [26, 23, 19], "weight": 0.400146484375}, {"color": [83, 74, 65], "weight": 0.086181640625}, {"color": [122, 121, 120], "weight": 0.076171875}], "entropy": 5.199400452368815, "size": 7190}, {"caption": null, "url": "https://pbs.twimg.com/profile_images/3006744716/0b051d7b2dd5e4c2d024f3af62087414_normal.jpeg", "height": 48, "width": 48, "colors": [{"color": [18, 13, 24], "weight": 0.134521484375}, {"color": [32, 27, 123], "weight": 0.06884765625}, {"color": [67, 56, 167], "weight": 0.0537109375}, {"color": [203, 222, 248], "weight": 0.0419921875}, {"color": [78, 73, 124], "weight": 0.033447265625}], "entropy": 6.71550260751, "size": 1123}, {"caption": null, "url": "https://pbs.twimg.com/profile_images/378800000831796892/3279fb8343bd096dcb6527135e38c0d2_normal.jpeg", "height": 48, "width": 48, "colors": [{"color": [0, 2, 6], "weight": 0.25390625}, {"color": [238, 236, 31], "weight": 0.180908203125}, {"color": [168, 169, 38], "weight": 0.051513671875}, {"color": [128, 125, 19], "weight": 0.038330078125}, {"color": [75, 73, 4], "weight": 0.037841796875}], "entropy": 4.20562174251, "size": 2177}], "cache_age": 86400, "lead": null, "language": "English", "original_url": "http://twitter.com/FreeCooperUnion/status/333676507048312832/photo/1", "url": "https://twitter.com/FreeCooperUnion/status/333676507048312832", "media": {"url": "https://pbs.twimg.com/media/BKF1A-kCAAAq0Jq.jpg:large", "width": 1024, "type": "photo", "height": 765}, "title": "Twitter / FreeCooperUnion: Drawing class in Peter Cooper ...", "offset": null, "content": null, "entities": [{"count": 2, "name": "Peter Cooper Park"}, {"count": 1, "name": "United States"}], "favicon_colors": [{"color": [0, 174, 233], "weight": 0.031494140625}, {"color": [245, 249, 250], "weight": 0.031005859375}], "keywords": [{"score": 20, "name": "y4posmgk5p"}, {"score": 20, "name": "sax"}, {"score": 20, "name": "bhqfu"}, {"score": 16, "name": "location"}, {"score": 12, "name": "tweet"}, {"score": 11, "name": "pic"}, {"score": 10, "name": "40404"}, {"score": 10, "name": "freecooperunion"}, {"score": 9, "name": "peter"}, {"score": 9, "name": "twitter"}], "published": null, "provider_name": "Twitter", "type": "html"}