{"provider_url": "http://twitter.com", "description": "Cooper Union's new price tag. Brought to you by a admin and board who care about profits, not education pic.twitter.com/onKlMQmGqI", "embeds": [], "safe": true, "provider_display": "twitter.com", "related": [], "favicon_url": "https://abs.twimg.com/favicons/favicon.ico", "authors": [{"url": "http://twitter.com/FreeCooperUnion", "name": "FreeCooperUnion"}], "images": [{"caption": null, "url": "https://pbs.twimg.com/media/BIkOIvyCMAEqnPR.jpg:large", "height": 768, "width": 1024, "colors": [{"color": [99, 96, 95], "weight": 0.312255859375}, {"color": [177, 179, 171], "weight": 0.2294921875}, {"color": [137, 138, 134], "weight": 0.213623046875}, {"color": [38, 43, 48], "weight": 0.150390625}, {"color": [226, 126, 108], "weight": 0.09423828125}], "entropy": 6.03945410184, "size": 89043}, {"caption": null, "url": "https://pbs.twimg.com/media/BIkOIvyCMAEqnPR.jpg", "height": 450, "width": 600, "colors": [{"color": [100, 100, 100], "weight": 0.37939453125}, {"color": [150, 151, 147], "weight": 0.233154296875}, {"color": [40, 45, 48], "weight": 0.158203125}, {"color": [182, 186, 177], "weight": 0.112060546875}, {"color": [244, 128, 104], "weight": 0.071044921875}], "entropy": 5.814046656964341, "size": 40153}, {"caption": null, "url": "https://pbs.twimg.com/profile_images/414166548165582849/9qklcopT_normal.jpeg", "height": 48, "width": 48, "colors": [{"color": [213, 237, 36], "weight": 0.429443359375}, {"color": [62, 124, 34], "weight": 0.0458984375}, {"color": [19, 80, 11], "weight": 0.03173828125}, {"color": [105, 163, 65], "weight": 0.031005859375}, {"color": [0, 42, 4], "weight": 0.0244140625}], "entropy": 3.83681492319, "size": 1559}, {"caption": null, "url": "https://pbs.twimg.com/profile_images/378800000408436594/2c2b7d1159168726ad8cc63c8a88d1d7_normal.jpeg", "height": 48, "width": 48, "colors": [{"color": [164, 185, 200], "weight": 0.22509765625}, {"color": [41, 38, 36], "weight": 0.167236328125}, {"color": [84, 78, 79], "weight": 0.086181640625}, {"color": [128, 134, 144], "weight": 0.083984375}], "entropy": 5.7537124717, "size": 7190}, {"caption": null, "url": "https://pbs.twimg.com/profile_images/378800000564590722/65994ad023b6cf809224fb4d4dd158cf_normal.jpeg", "height": 48, "width": 48, "colors": [{"color": [29, 26, 32], "weight": 0.163818359375}, {"color": [182, 141, 90], "weight": 0.113037109375}, {"color": [89, 57, 41], "weight": 0.105712890625}, {"color": [127, 91, 72], "weight": 0.07373046875}, {"color": [159, 110, 62], "weight": 0.058837890625}], "entropy": 6.488109454100403, "size": 7190}], "cache_age": 86400, "lead": null, "language": "English", "original_url": "http://twitter.com/FreeCooperUnion/status/326807991384944640/photo/1", "url": "https://twitter.com/FreeCooperUnion/status/326807991384944640", "media": {"url": "https://pbs.twimg.com/media/BIkOIvyCMAEqnPR.jpg:large", "width": 1024, "type": "photo", "height": 768}, "title": "Twitter / FreeCooperUnion: Cooper Union's new price tag. ...", "offset": null, "content": null, "entities": [{"count": 2, "name": "Cooper Union"}, {"count": 1, "name": "United States"}], "favicon_colors": [{"color": [0, 171, 232], "weight": 0.033203125}, {"color": [242, 250, 252], "weight": 0.029296875}], "keywords": [{"score": 20, "name": "onklmqmgqi"}, {"score": 20, "name": "admin"}, {"score": 20, "name": "freecooperunion"}, {"score": 16, "name": "location"}, {"score": 11, "name": "pic"}, {"score": 10, "name": "40404"}, {"score": 9, "name": "twitter"}, {"score": 9, "name": "tag"}, {"score": 8, "name": "cooper"}, {"score": 8, "name": "tweet"}], "published": null, "provider_name": "Twitter", "type": "html"}