{"provider_url": "http://twitter.com", "description": "Crowd is gathering outside of cooper! pic.twitter.com/6c9KNmYzGF", "embeds": [], "safe": true, "provider_display": "twitter.com", "related": [], "favicon_url": "https://abs.twimg.com/favicons/favicon.ico", "authors": [{"url": "http://twitter.com/FreeCooperUnion", "name": "FreeCooperUnion"}], "images": [{"caption": null, "url": "https://pbs.twimg.com/media/BJM_asoCcAAuZB7.jpg:large", "height": 768, "width": 1024, "colors": [{"color": [21, 19, 20], "weight": 0.271728515625}, {"color": [119, 102, 93], "weight": 0.203125}, {"color": [140, 135, 125], "weight": 0.200439453125}, {"color": [70, 59, 54], "weight": 0.192626953125}, {"color": [189, 184, 170], "weight": 0.0751953125}], "entropy": 6.78753269918, "size": 150914}, {"caption": null, "url": "https://pbs.twimg.com/media/BJM_asoCcAAuZB7.jpg", "height": 450, "width": 600, "colors": [{"color": [20, 18, 18], "weight": 0.2666015625}, {"color": [138, 130, 121], "weight": 0.233642578125}, {"color": [111, 97, 89], "weight": 0.19873046875}, {"color": [66, 57, 51], "weight": 0.18359375}, {"color": [187, 179, 164], "weight": 0.062744140625}], "entropy": 6.819845465215343, "size": 67942}, {"caption": null, "url": "https://pbs.twimg.com/profile_images/2552819317/image_normal.jpg", "height": 48, "width": 48, "colors": [{"color": [245, 246, 248], "weight": 0.325439453125}, {"color": [7, 15, 21], "weight": 0.111328125}, {"color": [113, 112, 116], "weight": 0.033935546875}, {"color": [190, 184, 187], "weight": 0.03369140625}, {"color": [147, 146, 150], "weight": 0.031494140625}], "entropy": 3.6525615933, "size": 7190}, {"caption": null, "url": "https://pbs.twimg.com/profile_images/378800000005983616/bd4a62d8e7fd6355528d2fe89976539b_normal.jpeg", "height": 48, "width": 48, "colors": [{"color": [202, 179, 165], "weight": 0.27099609375}, {"color": [150, 122, 97], "weight": 0.149658203125}, {"color": [18, 11, 11], "weight": 0.096923828125}, {"color": [94, 68, 56], "weight": 0.044921875}], "entropy": 6.08251086797, "size": 1047}, {"caption": null, "url": "https://pbs.twimg.com/profile_images/378800000831796892/3279fb8343bd096dcb6527135e38c0d2_normal.jpeg", "height": 48, "width": 48, "colors": [{"color": [0, 2, 6], "weight": 0.25390625}, {"color": [238, 236, 31], "weight": 0.180908203125}, {"color": [168, 169, 38], "weight": 0.051513671875}, {"color": [128, 125, 19], "weight": 0.038330078125}, {"color": [75, 73, 4], "weight": 0.037841796875}], "entropy": 4.20562174251, "size": 2177}], "cache_age": 86400, "lead": null, "language": "English", "original_url": "http://twitter.com/FreeCooperUnion/status/329676925608030208/photo/1", "url": "https://twitter.com/FreeCooperUnion/status/329676925608030208", "media": {"url": "https://pbs.twimg.com/media/BJM_asoCcAAuZB7.jpg:large", "width": 1024, "type": "photo", "height": 768}, "title": "Twitter / FreeCooperUnion: Crowd is gathering outside ...", "offset": null, "content": null, "entities": [{"count": 1, "name": "United States"}], "favicon_colors": [{"color": [241, 248, 251], "weight": 0.03662109375}, {"color": [0, 172, 231], "weight": 0.02587890625}], "keywords": [{"score": 20, "name": "6c9knmyzgf"}, {"score": 20, "name": "freecooperunion"}, {"score": 17, "name": "pic"}, {"score": 16, "name": "location"}, {"score": 13, "name": "cooper"}, {"score": 13, "name": "twitter"}, {"score": 12, "name": "gathering"}, {"score": 11, "name": "crowd"}, {"score": 10, "name": "freeu"}, {"score": 10, "name": "outside"}], "published": null, "provider_name": "Twitter", "type": "html"}