{"provider_url": "http://twitter.com", "description": "@MarquardtA Banners show solidarity with #Gezi movement at New York City's Cooper Union (2/2) #wearegezi pic.twitter.com/H0N8T2LOth", "embeds": [], "safe": true, "provider_display": "twitter.com", "related": [], "favicon_url": "https://abs.twimg.com/favicons/favicon.ico", "authors": [{"url": "http://twitter.com/kilmer", "name": "kilmer"}], "images": [{"caption": null, "url": "https://pbs.twimg.com/media/BNDgU-eCUAA_-1b.jpg:large", "height": 764, "width": 1024, "colors": [{"color": [218, 223, 216], "weight": 0.24951171875}, {"color": [203, 175, 153], "weight": 0.205810546875}, {"color": [97, 83, 73], "weight": 0.19189453125}, {"color": [37, 27, 23], "weight": 0.182861328125}, {"color": [153, 137, 124], "weight": 0.169921875}], "entropy": 6.25277481664, "size": 149734}, {"caption": null, "url": "https://pbs.twimg.com/media/BNDgU-eCUAA_-1b.jpg", "height": 447, "width": 599, "colors": [{"color": [34, 25, 22], "weight": 0.193603515625}, {"color": [95, 81, 71], "weight": 0.185302734375}, {"color": [217, 235, 235], "weight": 0.17822265625}, {"color": [201, 170, 147], "weight": 0.1611328125}, {"color": [220, 193, 168], "weight": 0.142822265625}], "entropy": 6.074670902826798, "size": 68844}, {"caption": null, "url": "https://pbs.twimg.com/profile_images/3556890844/248e7333d012a2d38b51d7b1e6c763b8_normal.jpeg", "height": 48, "width": 48, "colors": [{"color": [109, 110, 200], "weight": 0.31787109375}, {"color": [16, 45, 146], "weight": 0.199951171875}, {"color": [5, 10, 32], "weight": 0.03173828125}, {"color": [55, 67, 58], "weight": 0.012939453125}], "entropy": 5.983053531679848, "size": 929}], "cache_age": 86400, "lead": null, "language": "English", "original_url": "http://twitter.com/kilmer/status/347023822270124033/photo/1", "url": "https://twitter.com/kilmer/status/347023822270124033", "media": {"url": "https://pbs.twimg.com/media/BNDgU-eCUAA_-1b.jpg:large", "width": 1024, "type": "photo", "height": 764}, "title": "Twitter / kilmer: @MarquardtA Banners show ...", "offset": null, "content": null, "entities": [{"count": 2, "name": "New York City"}, {"count": 2, "name": "Cooper Union"}, {"count": 1, "name": "United States"}], "favicon_colors": [{"color": [0, 174, 233], "weight": 0.03173828125}, {"color": [239, 247, 252], "weight": 0.03076171875}], "keywords": [{"score": 20, "name": "h0n8t2loth"}, {"score": 20, "name": "wearegezi"}, {"score": 20, "name": "gezi"}, {"score": 20, "name": "marquardta"}, {"score": 16, "name": "location"}, {"score": 12, "name": "tweet"}, {"score": 12, "name": "banners"}, {"score": 12, "name": "solidarity"}, {"score": 11, "name": "pic"}, {"score": 10, "name": "40404"}], "published": null, "provider_name": "Twitter", "type": "html"}