{"provider_url": "http://twitter.com", "description": "@ericwareheim visited the Presidents office occupation today. Awesome. pic.twitter.com/iBKDq5kTO6", "embeds": [], "safe": true, "provider_display": "twitter.com", "related": [], "favicon_url": "https://abs.twimg.com/favicons/favicon.ico", "authors": [{"url": "http://twitter.com/FreeCooperUnion", "name": "FreeCooperUnion"}], "images": [{"caption": null, "url": "https://pbs.twimg.com/media/BKXQvyUCUAEg-xw.jpg:large", "height": 960, "width": 720, "colors": [{"color": [91, 91, 91], "weight": 0.320556640625}, {"color": [151, 149, 138], "weight": 0.259033203125}, {"color": [47, 51, 55], "weight": 0.239501953125}, {"color": [196, 196, 184], "weight": 0.1298828125}, {"color": [239, 241, 234], "weight": 0.051025390625}], "entropy": 6.29762878202, "size": 85321}, {"caption": null, "url": "https://pbs.twimg.com/media/BKXQvyUCUAEg-xw.jpg", "height": 800, "width": 600, "colors": [{"color": [86, 88, 88], "weight": 0.32421875}, {"color": [150, 148, 137], "weight": 0.27734375}, {"color": [44, 47, 49], "weight": 0.22802734375}, {"color": [198, 197, 183], "weight": 0.126220703125}, {"color": [238, 243, 236], "weight": 0.044189453125}], "entropy": 6.218625224229191, "size": 62087}, {"caption": null, "url": "https://pbs.twimg.com/profile_images/378800000147173010/7c359e540a238e3a4257712edbe1e2eb_normal.jpeg", "height": 48, "width": 48, "colors": [{"color": [245, 246, 244], "weight": 0.43994140625}, {"color": [150, 146, 102], "weight": 0.03857421875}, {"color": [113, 104, 53], "weight": 0.037841796875}, {"color": [36, 32, 14], "weight": 0.025146484375}, {"color": [76, 68, 37], "weight": 0.02099609375}], "entropy": 2.780752847302493, "size": 999}, {"caption": null, "url": "https://pbs.twimg.com/profile_images/3084698543/950ebbc8532dc80c9fbaae2c81fd3641_normal.jpeg", "height": 48, "width": 48, "colors": [{"color": [245, 245, 245], "weight": 0.427001953125}, {"color": [146, 146, 146], "weight": 0.095703125}, {"color": [79, 79, 79], "weight": 0.039794921875}], "entropy": 2.22731656029, "size": 7190}, {"caption": null, "url": "https://pbs.twimg.com/profile_images/378800000763160764/878632134576e75626199ce67b0c39b4_normal.jpeg", "height": 48, "width": 48, "colors": [{"color": [236, 237, 239], "weight": 0.3515625}, {"color": [49, 52, 58], "weight": 0.12353515625}, {"color": [110, 114, 120], "weight": 0.08740234375}], "entropy": 3.35137282142, "size": 1761}], "cache_age": 86400, "lead": null, "language": "English", "original_url": "http://twitter.com/FreeCooperUnion/status/334903266683015168/photo/1", "url": "https://twitter.com/FreeCooperUnion/status/334903266683015168", "media": {"url": "https://pbs.twimg.com/media/BKXQvyUCUAEg-xw.jpg:large", "width": 720, "type": "photo", "height": 960}, "title": "Twitter / FreeCooperUnion: .@ericwareheim visited the ...", "offset": null, "content": null, "entities": [{"count": 1, "name": "United States"}, {"count": 1, "name": "Eric"}], "favicon_colors": [{"color": [240, 249, 253], "weight": 0.033447265625}, {"color": [0, 173, 234], "weight": 0.029052734375}], "keywords": [{"score": 30, "name": "ericwareheim"}, {"score": 20, "name": "ibkdq5kto6"}, {"score": 20, "name": "freecooperunion"}, {"score": 16, "name": "location"}, {"score": 11, "name": "awesome"}, {"score": 11, "name": "pic"}, {"score": 11, "name": "occupation"}, {"score": 10, "name": "freecooper"}, {"score": 10, "name": "40404"}, {"score": 10, "name": "whaaat"}], "published": null, "provider_name": "Twitter", "type": "html"}